hypertor/__init__.py
hypertor/_hypertor.cpython-311-x86_64-linux-gnu.so
hypertor/_hypertor.pyi
hypertor/py.typed
hypertor-0.2.2.dist-info/METADATA
hypertor-0.2.2.dist-info/WHEEL
hypertor-0.2.2.dist-info/licenses/LICENSE
hypertor-0.2.2.dist-info/RECORD
