Metadata-Version: 2.4
Name: hypertor
Version: 0.2.2
Classifier: Development Status :: 4 - Beta
Classifier: Intended Audience :: Developers
Classifier: License :: OSI Approved :: MIT License
Classifier: License :: OSI Approved :: Apache Software License
Classifier: Operating System :: OS Independent
Classifier: Programming Language :: Python :: 3
Classifier: Programming Language :: Python :: 3.9
Classifier: Programming Language :: Python :: 3.10
Classifier: Programming Language :: Python :: 3.11
Classifier: Programming Language :: Python :: 3.12
Classifier: Programming Language :: Python :: 3.13
Classifier: Programming Language :: Rust
Classifier: Topic :: Internet :: WWW/HTTP
Classifier: Topic :: Security
Classifier: Typing :: Typed
Classifier: Framework :: FastAPI
Requires-Dist: pytest>=8.0 ; extra == 'dev'
Requires-Dist: pytest-asyncio>=0.23 ; extra == 'dev'
Requires-Dist: mypy>=1.8 ; extra == 'dev'
Requires-Dist: ruff>=0.2 ; extra == 'dev'
Provides-Extra: dev
License-File: LICENSE
Summary: Best-in-class Tor HTTP client and server library - consume AND host .onion services
Keywords: tor,http,privacy,anonymity,onion,hidden-service,fastapi
Author: hupe1980
License: MIT
Requires-Python: >=3.9
Project-URL: Documentation, https://hupe1980.github.io/hypertor
Project-URL: Homepage, https://hupe1980.github.io/hypertor
Project-URL: Repository, https://github.com/hupe1980/hypertor
